README.rst
setup.py
django_assr.egg-info/PKG-INFO
django_assr.egg-info/SOURCES.txt
django_assr.egg-info/dependency_links.txt
django_assr.egg-info/requires.txt
django_assr.egg-info/top_level.txt
djassr/__init__.py
djassr/apps.py
djassr/serializers.py
djassr/views.py