Metadata-Version: 1.1
Name: django-assr
Version: 0.1.0
Summary: Django AWS S3 Signed Requests API with Django Rest Framework
Home-page: https://github.com/alej0varas/djassr
Author: Alexandre Varas
Author-email: alej0varas@gmail.com
License: GNU Library or Lesser General Public License (LGPL)
Platform: UNKNOWN
Classifier: Development Status :: 3 - Alpha
Classifier: Environment :: Web Environment
Classifier: Framework :: Django :: 1.9
Classifier: Intended Audience :: Developers
Classifier: License :: OSI Approved :: GNU Library or Lesser General Public License (LGPL)
Classifier: Operating System :: OS Independent
Classifier: Programming Language :: Python
Classifier: Programming Language :: Python :: 3
